iris/__init__.py
iris/__main__.py
iris/dataset.py
iris/meta.py
iris/plugins.py
iris/powder.py
iris/raw.py
iris/gui/__init__.py
iris/gui/angular_average_dialog.py
iris/gui/bragg_peak_dialog.py
iris/gui/calibrate_q_dialog.py
iris/gui/control_bar.py
iris/gui/controller.py
iris/gui/data_viewer.py
iris/gui/gui.py
iris/gui/metadata_edit_dialog.py
iris/gui/powder_viewer.py
iris/gui/processing_dialog.py
iris/gui/qbusyindicator.py
iris/gui/qlogger.py
iris/gui/symmetrize_dialog.py
iris/gui/time_series_widget.py
iris/gui/update.py
iris/tests/__init__.py
iris/tests/broken_plugin.py
iris/tests/plugin_fixture.py
iris/tests/test_dataset.py
iris/tests/test_plugins.py
iris/tests/test_powder.py
iris/tests/test_raw.py
iris_ued-5.3.5.dist-info/LICENSE.txt
iris_ued-5.3.5.dist-info/METADATA
iris_ued-5.3.5.dist-info/WHEEL
iris_ued-5.3.5.dist-info/entry_points.txt
iris_ued-5.3.5.dist-info/top_level.txt
iris_ued-5.3.5.dist-info/RECORD
