Metadata-Version: 2.1
Name: iris-ued
Version: 5.3.5
Summary: Ultrafast electron diffraction data exploration
Home-page: http://iris-ued.readthedocs.io
Author: Laurent P. René de Cotret
Author-email: laurent.renedecotret@mail.mcgill.ca
Maintainer: Laurent P. René de Cotret
Maintainer-email: laurent.renedecotret@mail.mcgill.ca
License: GPLv3
Download-URL: http://github.com/LaurentRDC/iris-ued
Project-URL: Documentation, http://iris-ued.readthedocs.io/en/master/
Project-URL: Source, https://github.com/LaurentRDC/iris-ued
Project-URL: Tracker, https://github.com/LaurentRDC/iris-ued/issues
Project-URL: Home, http://www.physics.mcgill.ca/siwicklab/software.html
Keywords: ultrafast electron diffraction visualization pyqtgraph
Platform: UNKNOWN
Classifier: Development Status :: 5 - Production/Stable
Classifier: Intended Audience :: Science/Research
Classifier: Topic :: Scientific/Engineering
Classifier: Topic :: Scientific/Engineering :: Physics
Classifier: Topic :: Scientific/Engineering :: Chemistry
Classifier: Topic :: Scientific/Engineering :: Visualization
Classifier: License :: OSI Approved :: GNU General Public License v3 (GPLv3)
Classifier: Natural Language :: English
Classifier: Operating System :: OS Independent
Classifier: Programming Language :: Python
Classifier: Programming Language :: Python :: 3.8
Classifier: Programming Language :: Python :: 3.9
Classifier: Programming Language :: Python :: 3.10
Classifier: Programming Language :: Python :: 3.11
Classifier: Programming Language :: Python :: Implementation :: CPython
Requires-Python: >= 3.8
License-File: LICENSE.txt
Requires-Dist: numpy (<2,>=1.22)
Requires-Dist: scipy (>=1.0.0)
Requires-Dist: h5py (>=2.10.0)
Requires-Dist: PyQt5 (<6,>=5.15)
Requires-Dist: crystals (<2,>=1.3.0)
Requires-Dist: scikit-ued (<3,>=2.1.4)
Requires-Dist: qdarkstyle (<3,>=2.8)
Requires-Dist: pyqtgraph (>=0.11)
Requires-Dist: npstreams (<2,>=1.6.5)
Requires-Dist: packaging (>=20)
